dustpy/__init__.py
dustpy/simulation.py
dustpy/constants/__init__.py
dustpy/constants/_constants_f.cpython-38-x86_64-linux-gnu.so
dustpy/plot/__init__.py
dustpy/plot/plot.py
dustpy/std/__init__.py
dustpy/std/dust.py
dustpy/std/dust_f.cpython-38-x86_64-linux-gnu.so
dustpy/std/gas.py
dustpy/std/gas_f.cpython-38-x86_64-linux-gnu.so
dustpy/std/grid.py
dustpy/std/sim.py
dustpy/std/star.py
dustpy/utils/__init__.py
dustpy/utils/boundary.py
dustpy/utils/version.py
dustpy-0.4.6.dist-info/LICENSE
dustpy-0.4.6.dist-info/METADATA
dustpy-0.4.6.dist-info/WHEEL
dustpy-0.4.6.dist-info/top_level.txt
dustpy-0.4.6.dist-info/RECORD
