Metadata-Version: 2.1
Name: dustpy
Version: 0.4.6
Summary: Dust evolution in protoplanetary disks
Home-page: https://github.com/stammler/dustpy
Author: Sebastian Stammler, Til Birnstiel
Author-email: stammler@usm.lmu.de, til.birnstiel@lmu.de
Maintainer: Sebastian Stammler
License: GPLv3
Project-URL: Source Code, https://github.com/stammler/dustpy/
Project-URL: Documentation, https://stammler.github.io/dustpy/
Keywords: numerical,simulation,science,physics,astrophysics,astronomy
Platform: UNKNOWN
Classifier: Development Status :: 3 - Alpha
Classifier: Environment :: Console
Classifier: Intended Audience :: Developers
Classifier: Intended Audience :: Science/Research
Classifier: License :: OSI Approved :: GNU General Public License v3 (GPLv3)
Classifier: Natural Language :: English
Classifier: Operating System :: OS Independent
Classifier: Programming Language :: Python
Classifier: Programming Language :: Python :: 3 :: Only
Classifier: Topic :: Education
Classifier: Topic :: Scientific/Engineering
Classifier: Topic :: Scientific/Engineering :: Physics
Requires-Dist: matplotlib
Requires-Dist: numpy
Requires-Dist: simframe
